LICENSE
MANIFEST.in
README
setup.py
django_readonlywidget/__init__.py
django_readonlywidget/widgets.py
django_readonlywidget.egg-info/PKG-INFO
django_readonlywidget.egg-info/SOURCES.txt
django_readonlywidget.egg-info/dependency_links.txt
django_readonlywidget.egg-info/not-zip-safe
django_readonlywidget.egg-info/top_level.txt