Metadata-Version: 1.0
Name: django-readonlywidget
Version: 0.2
Summary: A ReadOnly Widget for Django
Home-page: http://bitbucket.org/stephrdev/django-readonlywidget/src/
Author: Stephan Jaekel
Author-email: steph@rdev.info
License: UNKNOWN
Platform: UNKNOWN
Classifier: Development Status :: 3 - Alpha
Classifier: Environment :: Web Environment
Classifier: Intended Audience :: Developers
Classifier: License :: OSI Approved :: BSD License
Classifier: Operating System :: OS Independent
Classifier: Programming Language :: Python
Classifier: Framework :: Django
